trainingsetai/__init__.py
trainingsetai-0.0.2.dist-info/LICENSE
trainingsetai-0.0.2.dist-info/METADATA
trainingsetai-0.0.2.dist-info/WHEEL
trainingsetai-0.0.2.dist-info/top_level.txt
trainingsetai-0.0.2.dist-info/RECORD
