Metadata-Version: 2.1
Name: trainingsetai
Version: 0.0.2
Summary: The official Python SDK for Trainingset.ai.
Home-page: https://github.com/trainingset-ai/trainingsetai-python-sdk
Author: Trainingset.ai
Author-email: contactus@trainingset.ai
License: UNKNOWN
Platform: UNKNOWN
Classifier: Programming Language :: Python
Classifier: Development Status :: 5 - Production/Stable
Classifier: License :: OSI Approved :: MIT License
Classifier: Intended Audience :: Developers
Classifier: Operating System :: OS Independent
Classifier: Topic :: Software Development :: Libraries
